app/__init__.py
app/clipboard.py
app/config.py
app/version.py
klippy-0.2.0.data/scripts/cli.py
klippy-0.2.0.dist-info/LICENSE
klippy-0.2.0.dist-info/METADATA
klippy-0.2.0.dist-info/WHEEL
klippy-0.2.0.dist-info/entry_points.txt
klippy-0.2.0.dist-info/top_level.txt
klippy-0.2.0.dist-info/RECORD
